mkdocs_breadcrumbs/__init__.py
mkdocs_breadcrumbs/plugin.py
mkdocs_breadcrumbs-0.0.3.dist-info/LICENSE
mkdocs_breadcrumbs-0.0.3.dist-info/METADATA
mkdocs_breadcrumbs-0.0.3.dist-info/WHEEL
mkdocs_breadcrumbs-0.0.3.dist-info/entry_points.txt
mkdocs_breadcrumbs-0.0.3.dist-info/top_level.txt
mkdocs_breadcrumbs-0.0.3.dist-info/RECORD
