Metadata-Version: 2.1
Name: mkdocs-breadcrumbs
Version: 0.0.3
Summary: Location-based breadcrumbs.
Home-page: https://github.com/mihaigalos/mkdocs-breadcrumbs
Author: Mihai Galos
Author-email: mihai@galos.one
License: MIT
Keywords: mkdocs plugin
Classifier: Operating System :: OS Independent
Classifier: Programming Language :: Python
Classifier: Programming Language :: Python :: 3
Classifier: Programming Language :: Python :: 3.8
Classifier: Programming Language :: Python :: 3.9
Classifier: Programming Language :: Python :: 3.10
Classifier: Programming Language :: Python :: 3.11
Classifier: License :: OSI Approved :: MIT License
Requires-Python: >=3.8
License-File: LICENSE
Requires-Dist: mkdocs >=1.0.4
Requires-Dist: mkdocs-material
